{"id": 78584, "name": "科技传播前沿讲座", "courseCode": "025M01", "lessonCode": "025M01.01", "teacherName": "周荣庭, 梁琰", "lectures": [{"startDate": 1436233500, "endDate": 1436242200, "name": "科技传播前沿讲座", "location": "2103", "teacherName": "梁琰,周荣庭", "periods": 3.0, "startIndex": 3, "endIndex": 5, "startHHMM": 945, "endHHMM": 1210, "additionalInfo": {}}, {"startDate": 1436406300, "endDate": 1436415000, "name": "科技传播前沿讲座", "location": "2103", "teacherName": "梁琰,周荣庭", "periods": 3.0, "startIndex": 3, "endIndex": 5, "startHHMM": 945, "endHHMM": 1210, "additionalInfo": {}}, {"startDate": 1436579100, "endDate": 1436587800, "name": "科技传播前沿讲座", "location": "2103", "teacherName": "梁琰,周荣庭", "periods": 3.0, "startIndex": 3, "endIndex": 5, "startHHMM": 945, "endHHMM": 1210, "additionalInfo": {}}, {"startDate": 1436838300, "endDate": 1436847000, "name": "科技传播前沿讲座", "location": "2103", "teacherName": "梁琰,周荣庭", "periods": 3.0, "startIndex": 3, "endIndex": 5, "startHHMM": 945, "endHHMM": 1210, "additionalInfo": {}}, {"startDate": 1437011100, "endDate": 1437019800, "name": "科技传播前沿讲座", "location": "2103", "teacherName": "梁琰,周荣庭", "periods": 3.0, "startIndex": 3, "endIndex": 5, "startHHMM": 945, "endHHMM": 1210, "additionalInfo": {}}, {"startDate": 1437183900, "endDate": 1437192600, "name": "科技传播前沿讲座", "location": "2103", "teacherName": "梁琰,周荣庭", "periods": 3.0, "startIndex": 3, "endIndex": 5, "startHHMM": 945, "endHHMM": 1210, "additionalInfo": {}}], "exams": [], "dateTimePlacePersonText": "1~2周 2103 :2(3,5) 梁琰\n1~2周 2103 :2(3,5) 周荣庭\n1~2周 2103 :4(3,5) 梁琰\n1~2周 2103 :4(3,5) 周荣庭\n1~2周 2103 :6(3,5) 梁琰\n1~2周 2103 :6(3,5) 周荣庭", "courseType": "理论课", "courseGradation": "通修", "courseCategory": "本科计划内课程", "educationType": "本科", "classType": "通识", "openDepartment": "科技传播与科技政策系", "description": "", "credit": 1.0, "additionalInfo": {}}