{"id": 94932, "name": "创新工程实践", "courseCode": "HS00M05", "lessonCode": "HS00M05.01", "teacherName": "慕课教师, 李玉虎", "lectures": [{"startDate": 1486857000, "endDate": 1486859700, "name": "创新工程实践", "location": "", "teacherName": "李玉虎,慕课教师", "periods": 1.0, "startIndex": 1, "endIndex": 1, "startHHMM": 750, "endHHMM": 835, "additionalInfo": {}}, {"startDate": 1487461800, "endDate": 1487464500, "name": "创新工程实践", "location": "", "teacherName": "李玉虎,慕课教师", "periods": 1.0, "startIndex": 1, "endIndex": 1, "startHHMM": 750, "endHHMM": 835, "additionalInfo": {}}, {"startDate": 1488066600, "endDate": 1488069300, "name": "创新工程实践", "location": "", "teacherName": "李玉虎,慕课教师", "periods": 1.0, "startIndex": 1, "endIndex": 1, "startHHMM": 750, "endHHMM": 835, "additionalInfo": {}}, {"startDate": 1488671400, "endDate": 1488674100, "name": "创新工程实践", "location": "", "teacherName": "李玉虎,慕课教师", "periods": 1.0, "startIndex": 1, "endIndex": 1, "startHHMM": 750, "endHHMM": 835, "additionalInfo": {}}, {"startDate": 1489276200, "endDate": 1489278900, "name": "创新工程实践", "location": "", "teacherName": "李玉虎,慕课教师", "periods": 1.0, "startIndex": 1, "endIndex": 1, "startHHMM": 750, "endHHMM": 835, "additionalInfo": {}}, {"startDate": 1489881000, "endDate": 1489883700, "name": "创新工程实践", "location": "", "teacherName": "李玉虎,慕课教师", "periods": 1.0, "startIndex": 1, "endIndex": 1, "startHHMM": 750, "endHHMM": 835, "additionalInfo": {}}, {"startDate": 1490485800, "endDate": 1490488500, "name": "创新工程实践", "location": "", "teacherName": "李玉虎,慕课教师", "periods": 1.0, "startIndex": 1, "endIndex": 1, "startHHMM": 750, "endHHMM": 835, "additionalInfo": {}}, {"startDate": 1491090600, "endDate": 1491093300, "name": "创新工程实践", "location": "", "teacherName": "李玉虎,慕课教师", "periods": 1.0, "startIndex": 1, "endIndex": 1, "startHHMM": 750, "endHHMM": 835, "additionalInfo": {}}, {"startDate": 1491695400, "endDate": 1491698100, "name": "创新工程实践", "location": "", "teacherName": "李玉虎,慕课教师", "periods": 1.0, "startIndex": 1, "endIndex": 1, "startHHMM": 750, "endHHMM": 835, "additionalInfo": {}}, {"startDate": 1492300200, "endDate": 1492302900, "name": "创新工程实践", "location": "", "teacherName": "李玉虎,慕课教师", "periods": 1.0, "startIndex": 1, "endIndex": 1, "startHHMM": 750, "endHHMM": 835, "additionalInfo": {}}, {"startDate": 1492905000, "endDate": 1492907700, "name": "创新工程实践", "location": "", "teacherName": "李玉虎,慕课教师", "periods": 1.0, "startIndex": 1, "endIndex": 1, "startHHMM": 750, "endHHMM": 835, "additionalInfo": {}}, {"startDate": 1493509800, "endDate": 1493512500, "name": "创新工程实践", "location": "", "teacherName": "李玉虎,慕课教师", "periods": 1.0, "startIndex": 1, "endIndex": 1, "startHHMM": 750, "endHHMM": 835, "additionalInfo": {}}, {"startDate": 1494114600, "endDate": 1494117300, "name": "创新工程实践", "location": "", "teacherName": "李玉虎,慕课教师", "periods": 1.0, "startIndex": 1, "endIndex": 1, "startHHMM": 750, "endHHMM": 835, "additionalInfo": {}}, {"startDate": 1494719400, "endDate": 1494722100, "name": "创新工程实践", "location": "", "teacherName": "李玉虎,慕课教师", "periods": 1.0, "startIndex": 1, "endIndex": 1, "startHHMM": 750, "endHHMM": 835, "additionalInfo": {}}, {"startDate": 1495324200, "endDate": 1495326900, "name": "创新工程实践", "location": "", "teacherName": "李玉虎,慕课教师", "periods": 1.0, "startIndex": 1, "endIndex": 1, "startHHMM": 750, "endHHMM": 835, "additionalInfo": {}}], "exams": [], "dateTimePlacePersonText": "1~15周  :7(1,1) 李玉虎\n1~15周  :7(1,1) 慕课", "courseType": "理论课", "courseGradation": "通修", "courseCategory": "核心通识", "educationType": "本科", "classType": "通识", "openDepartment": "人文与社会科学学院", "description": "", "credit": 3.0, "additionalInfo": {}}