{"id": 162823, "name": "极限飞盘", "courseCode": "PHED6406Q", "lessonCode": "PHED6406Q.02", "teacherName": "柴松", "lectures": [{"startDate": 1740613800, "endDate": 1740619500, "name": "极限飞盘", "location": "高新区操场", "teacherName": "柴松", "periods": 2.0, "startIndex": 1, "endIndex": 2, "startHHMM": 750, "endHHMM": 925, "additionalInfo": {}}, {"startDate": 1741218600, "endDate": 1741224300, "name": "极限飞盘", "location": "高新区操场", "teacherName": "柴松", "periods": 2.0, "startIndex": 1, "endIndex": 2, "startHHMM": 750, "endHHMM": 925, "additionalInfo": {}}, {"startDate": 1741823400, "endDate": 1741829100, "name": "极限飞盘", "location": "高新区操场", "teacherName": "柴松", "periods": 2.0, "startIndex": 1, "endIndex": 2, "startHHMM": 750, "endHHMM": 925, "additionalInfo": {}}, {"startDate": 1742428200, "endDate": 1742433900, "name": "极限飞盘", "location": "高新区操场", "teacherName": "柴松", "periods": 2.0, "startIndex": 1, "endIndex": 2, "startHHMM": 750, "endHHMM": 925, "additionalInfo": {}}, {"startDate": 1743033000, "endDate": 1743038700, "name": "极限飞盘", "location": "高新区操场", "teacherName": "柴松", "periods": 2.0, "startIndex": 1, "endIndex": 2, "startHHMM": 750, "endHHMM": 925, "additionalInfo": {}}, {"startDate": 1743637800, "endDate": 1743643500, "name": "极限飞盘", "location": "高新区操场", "teacherName": "柴松", "periods": 2.0, "startIndex": 1, "endIndex": 2, "startHHMM": 750, "endHHMM": 925, "additionalInfo": {}}, {"startDate": 1744242600, "endDate": 1744248300, "name": "极限飞盘", "location": "高新区操场", "teacherName": "柴松", "periods": 2.0, "startIndex": 1, "endIndex": 2, "startHHMM": 750, "endHHMM": 925, "additionalInfo": {}}, {"startDate": 1744847400, "endDate": 1744853100, "name": "极限飞盘", "location": "高新区操场", "teacherName": "柴松", "periods": 2.0, "startIndex": 1, "endIndex": 2, "startHHMM": 750, "endHHMM": 925, "additionalInfo": {}}, {"startDate": 1745452200, "endDate": 1745457900, "name": "极限飞盘", "location": "高新区操场", "teacherName": "柴松", "periods": 2.0, "startIndex": 1, "endIndex": 2, "startHHMM": 750, "endHHMM": 925, "additionalInfo": {}}, {"startDate": 1746661800, "endDate": 1746667500, "name": "极限飞盘", "location": "高新区操场", "teacherName": "柴松", "periods": 2.0, "startIndex": 1, "endIndex": 2, "startHHMM": 750, "endHHMM": 925, "additionalInfo": {}}, {"startDate": 1747266600, "endDate": 1747272300, "name": "极限飞盘", "location": "高新区操场", "teacherName": "柴松", "periods": 2.0, "startIndex": 1, "endIndex": 2, "startHHMM": 750, "endHHMM": 925, "additionalInfo": {}}, {"startDate": 1747871400, "endDate": 1747877100, "name": "极限飞盘", "location": "高新区操场", "teacherName": "柴松", "periods": 2.0, "startIndex": 1, "endIndex": 2, "startHHMM": 750, "endHHMM": 925, "additionalInfo": {}}, {"startDate": 1748476200, "endDate": 1748481900, "name": "极限飞盘", "location": "高新区操场", "teacherName": "柴松", "periods": 2.0, "startIndex": 1, "endIndex": 2, "startHHMM": 750, "endHHMM": 925, "additionalInfo": {}}, {"startDate": 1749081000, "endDate": 1749086700, "name": "极限飞盘", "location": "高新区操场", "teacherName": "柴松", "periods": 2.0, "startIndex": 1, "endIndex": 2, "startHHMM": 750, "endHHMM": 925, "additionalInfo": {}}, {"startDate": 1749685800, "endDate": 1749691500, "name": "极限飞盘", "location": "高新区操场", "teacherName": "柴松", "periods": 2.0, "startIndex": 1, "endIndex": 2, "startHHMM": 750, "endHHMM": 925, "additionalInfo": {}}], "exams": [], "dateTimePlacePersonText": "1~9,11~16周 高新区操场 :4(1,2) 柴松", "courseType": "理论课", "courseGradation": "硕士", "courseCategory": "研究生课程", "educationType": "研究生", "classType": "基础", "openDepartment": "体育教学中心", "description": "", "credit": 2.0, "additionalInfo": {}}