{"id": 164508, "name": "博弈论", "courseCode": "MBAD6427P", "lessonCode": "MBAD6427P.05", "teacherName": "王姚磊", "lectures": [{"startDate": 1741132200, "endDate": 1741137900, "name": "博弈论", "location": "国金院2-202", "teacherName": "王姚磊", "periods": 2.0, "startIndex": 1, "endIndex": 2, "startHHMM": 750, "endHHMM": 925, "additionalInfo": {}}, {"startDate": 1745365800, "endDate": 1745371500, "name": "博弈论", "location": "国金院2-202", "teacherName": "王姚磊", "periods": 2.0, "startIndex": 1, "endIndex": 2, "startHHMM": 750, "endHHMM": 925, "additionalInfo": {}}], "exams": [], "dateTimePlacePersonText": "2,9周 国金院2-202 :3(1,2) 王姚磊", "courseType": "理论课", "courseGradation": "硕士", "courseCategory": "研究生课程", "educationType": "研究生", "classType": "基础", "openDepartment": "MBA中心", "description": "", "credit": 2.0, "additionalInfo": {}}