{"id": 154888, "name": "科技写作与表达", "courseCode": "HS1501", "lessonCode": "HS1501.26", "teacherName": "孔燕", "lectures": [{"startDate": 1710415800, "endDate": 1710421500, "name": "科技写作与表达", "location": "2606", "teacherName": "孔燕", "periods": 2.0, "startIndex": 11, "endIndex": 12, "startHHMM": 1930, "endHHMM": 2105, "additionalInfo": {}}, {"startDate": 1710847800, "endDate": 1710853500, "name": "科技写作与表达", "location": "2606", "teacherName": "孔燕", "periods": 2.0, "startIndex": 11, "endIndex": 12, "startHHMM": 1930, "endHHMM": 2105, "additionalInfo": {}}, {"startDate": 1711625400, "endDate": 1711631100, "name": "科技写作与表达", "location": "2606", "teacherName": "孔燕", "periods": 2.0, "startIndex": 11, "endIndex": 12, "startHHMM": 1930, "endHHMM": 2105, "additionalInfo": {}}, {"startDate": 1712057400, "endDate": 1712063100, "name": "科技写作与表达", "location": "2606", "teacherName": "孔燕", "periods": 2.0, "startIndex": 11, "endIndex": 12, "startHHMM": 1930, "endHHMM": 2105, "additionalInfo": {}}, {"startDate": 1712662200, "endDate": 1712667900, "name": "科技写作与表达", "location": "2606", "teacherName": "孔燕", "periods": 2.0, "startIndex": 11, "endIndex": 12, "startHHMM": 1930, "endHHMM": 2105, "additionalInfo": {}}, {"startDate": 1713267000, "endDate": 1713272700, "name": "科技写作与表达", "location": "2606", "teacherName": "孔燕", "periods": 2.0, "startIndex": 11, "endIndex": 12, "startHHMM": 1930, "endHHMM": 2105, "additionalInfo": {}}, {"startDate": 1713871800, "endDate": 1713877500, "name": "科技写作与表达", "location": "2606", "teacherName": "孔燕", "periods": 2.0, "startIndex": 11, "endIndex": 12, "startHHMM": 1930, "endHHMM": 2105, "additionalInfo": {}}, {"startDate": 1715081400, "endDate": 1715087100, "name": "科技写作与表达", "location": "2606", "teacherName": "孔燕", "periods": 2.0, "startIndex": 11, "endIndex": 12, "startHHMM": 1930, "endHHMM": 2105, "additionalInfo": {}}, {"startDate": 1715686200, "endDate": 1715691900, "name": "科技写作与表达", "location": "2606", "teacherName": "孔燕", "periods": 2.0, "startIndex": 11, "endIndex": 12, "startHHMM": 1930, "endHHMM": 2105, "additionalInfo": {}}, {"startDate": 1716291000, "endDate": 1716296700, "name": "科技写作与表达", "location": "2606", "teacherName": "孔燕", "periods": 2.0, "startIndex": 11, "endIndex": 12, "startHHMM": 1930, "endHHMM": 2105, "additionalInfo": {}}], "exams": [], "dateTimePlacePersonText": "4~6(双),7~9,11~13周 2606 :2(11,12) 孔燕\n3~5(单)周 2606 :4(11,12) 孔燕", "courseType": "理论课", "courseGradation": "通修", "courseCategory": "核心通识", "educationType": "本科", "classType": "计划内与自由选修", "openDepartment": "少年班学院", "description": "", "credit": 1.0, "additionalInfo": {}}