{"id": 106824, "name": "数据结构与数据库", "courseCode": "210503", "lessonCode": "210503.03", "teacherName": "苏仕华", "lectures": [{"startDate": 1299109800, "endDate": 1299115500, "name": "数据结构与数据库", "location": "5402", "teacherName": "苏仕华", "periods": 2.0, "startIndex": 1, "endIndex": 2, "startHHMM": 750, "endHHMM": 925, "additionalInfo": {}}, {"startDate": 1299394200, "endDate": 1299400800, "name": "数据结构与数据库", "location": "5402", "teacherName": "苏仕华", "periods": 2.0, "startIndex": 7, "endIndex": 8, "startHHMM": 1450, "endHHMM": 1640, "additionalInfo": {}}, {"startDate": 1299714600, "endDate": 1299720300, "name": "数据结构与数据库", "location": "5402", "teacherName": "苏仕华", "periods": 2.0, "startIndex": 1, "endIndex": 2, "startHHMM": 750, "endHHMM": 925, "additionalInfo": {}}, {"startDate": 1299999000, "endDate": 1300005600, "name": "数据结构与数据库", "location": "5402", "teacherName": "苏仕华", "periods": 2.0, "startIndex": 7, "endIndex": 8, "startHHMM": 1450, "endHHMM": 1640, "additionalInfo": {}}, {"startDate": 1300319400, "endDate": 1300325100, "name": "数据结构与数据库", "location": "5402", "teacherName": "苏仕华", "periods": 2.0, "startIndex": 1, "endIndex": 2, "startHHMM": 750, "endHHMM": 925, "additionalInfo": {}}, {"startDate": 1300603800, "endDate": 1300610400, "name": "数据结构与数据库", "location": "5402", "teacherName": "苏仕华", "periods": 2.0, "startIndex": 7, "endIndex": 8, "startHHMM": 1450, "endHHMM": 1640, "additionalInfo": {}}, {"startDate": 1300924200, "endDate": 1300929900, "name": "数据结构与数据库", "location": "5402", "teacherName": "苏仕华", "periods": 2.0, "startIndex": 1, "endIndex": 2, "startHHMM": 750, "endHHMM": 925, "additionalInfo": {}}, {"startDate": 1301208600, "endDate": 1301215200, "name": "数据结构与数据库", "location": "5402", "teacherName": "苏仕华", "periods": 2.0, "startIndex": 7, "endIndex": 8, "startHHMM": 1450, "endHHMM": 1640, "additionalInfo": {}}, {"startDate": 1301529000, "endDate": 1301534700, "name": "数据结构与数据库", "location": "5402", "teacherName": "苏仕华", "periods": 2.0, "startIndex": 1, "endIndex": 2, "startHHMM": 750, "endHHMM": 925, "additionalInfo": {}}, {"startDate": 1301813400, "endDate": 1301820000, "name": "数据结构与数据库", "location": "5402", "teacherName": "苏仕华", "periods": 2.0, "startIndex": 7, "endIndex": 8, "startHHMM": 1450, "endHHMM": 1640, "additionalInfo": {}}, {"startDate": 1302133800, "endDate": 1302139500, "name": "数据结构与数据库", "location": "5402", "teacherName": "苏仕华", "periods": 2.0, "startIndex": 1, "endIndex": 2, "startHHMM": 750, "endHHMM": 925, "additionalInfo": {}}, {"startDate": 1302418200, "endDate": 1302424800, "name": "数据结构与数据库", "location": "5402", "teacherName": "苏仕华", "periods": 2.0, "startIndex": 7, "endIndex": 8, "startHHMM": 1450, "endHHMM": 1640, "additionalInfo": {}}, {"startDate": 1302738600, "endDate": 1302744300, "name": "数据结构与数据库", "location": "5402", "teacherName": "苏仕华", "periods": 2.0, "startIndex": 1, "endIndex": 2, "startHHMM": 750, "endHHMM": 925, "additionalInfo": {}}, {"startDate": 1303023000, "endDate": 1303029600, "name": "数据结构与数据库", "location": "5402", "teacherName": "苏仕华", "periods": 2.0, "startIndex": 7, "endIndex": 8, "startHHMM": 1450, "endHHMM": 1640, "additionalInfo": {}}, {"startDate": 1303343400, "endDate": 1303349100, "name": "数据结构与数据库", "location": "5402", "teacherName": "苏仕华", "periods": 2.0, "startIndex": 1, "endIndex": 2, "startHHMM": 750, "endHHMM": 925, "additionalInfo": {}}, {"startDate": 1303627800, "endDate": 1303634400, "name": "数据结构与数据库", "location": "5402", "teacherName": "苏仕华", "periods": 2.0, "startIndex": 7, "endIndex": 8, "startHHMM": 1450, "endHHMM": 1640, "additionalInfo": {}}, {"startDate": 1303948200, "endDate": 1303953900, "name": "数据结构与数据库", "location": "5402", "teacherName": "苏仕华", "periods": 2.0, "startIndex": 1, "endIndex": 2, "startHHMM": 750, "endHHMM": 925, "additionalInfo": {}}, {"startDate": 1304232600, "endDate": 1304239200, "name": "数据结构与数据库", "location": "5402", "teacherName": "苏仕华", "periods": 2.0, "startIndex": 7, "endIndex": 8, "startHHMM": 1450, "endHHMM": 1640, "additionalInfo": {}}, {"startDate": 1304553000, "endDate": 1304558700, "name": "数据结构与数据库", "location": "5402", "teacherName": "苏仕华", "periods": 2.0, "startIndex": 1, "endIndex": 2, "startHHMM": 750, "endHHMM": 925, "additionalInfo": {}}, {"startDate": 1304837400, "endDate": 1304844000, "name": "数据结构与数据库", "location": "5402", "teacherName": "苏仕华", "periods": 2.0, "startIndex": 7, "endIndex": 8, "startHHMM": 1450, "endHHMM": 1640, "additionalInfo": {}}, {"startDate": 1305157800, "endDate": 1305163500, "name": "数据结构与数据库", "location": "5402", "teacherName": "苏仕华", "periods": 2.0, "startIndex": 1, "endIndex": 2, "startHHMM": 750, "endHHMM": 925, "additionalInfo": {}}, {"startDate": 1305442200, "endDate": 1305448800, "name": "数据结构与数据库", "location": "5402", "teacherName": "苏仕华", "periods": 2.0, "startIndex": 7, "endIndex": 8, "startHHMM": 1450, "endHHMM": 1640, "additionalInfo": {}}, {"startDate": 1305762600, "endDate": 1305768300, "name": "数据结构与数据库", "location": "5402", "teacherName": "苏仕华", "periods": 2.0, "startIndex": 1, "endIndex": 2, "startHHMM": 750, "endHHMM": 925, "additionalInfo": {}}, {"startDate": 1306047000, "endDate": 1306053600, "name": "数据结构与数据库", "location": "5402", "teacherName": "苏仕华", "periods": 2.0, "startIndex": 7, "endIndex": 8, "startHHMM": 1450, "endHHMM": 1640, "additionalInfo": {}}, {"startDate": 1306367400, "endDate": 1306373100, "name": "数据结构与数据库", "location": "5402", "teacherName": "苏仕华", "periods": 2.0, "startIndex": 1, "endIndex": 2, "startHHMM": 750, "endHHMM": 925, "additionalInfo": {}}, {"startDate": 1306651800, "endDate": 1306658400, "name": "数据结构与数据库", "location": "5402", "teacherName": "苏仕华", "periods": 2.0, "startIndex": 7, "endIndex": 8, "startHHMM": 1450, "endHHMM": 1640, "additionalInfo": {}}, {"startDate": 1306972200, "endDate": 1306977900, "name": "数据结构与数据库", "location": "5402", "teacherName": "苏仕华", "periods": 2.0, "startIndex": 1, "endIndex": 2, "startHHMM": 750, "endHHMM": 925, "additionalInfo": {}}, {"startDate": 1307256600, "endDate": 1307263200, "name": "数据结构与数据库", "location": "5402", "teacherName": "苏仕华", "periods": 2.0, "startIndex": 7, "endIndex": 8, "startHHMM": 1450, "endHHMM": 1640, "additionalInfo": {}}, {"startDate": 1307577000, "endDate": 1307582700, "name": "数据结构与数据库", "location": "5402", "teacherName": "苏仕华", "periods": 2.0, "startIndex": 1, "endIndex": 2, "startHHMM": 750, "endHHMM": 925, "additionalInfo": {}}, {"startDate": 1307861400, "endDate": 1307868000, "name": "数据结构与数据库", "location": "5402", "teacherName": "苏仕华", "periods": 2.0, "startIndex": 7, "endIndex": 8, "startHHMM": 1450, "endHHMM": 1640, "additionalInfo": {}}, {"startDate": 1308181800, "endDate": 1308187500, "name": "数据结构与数据库", "location": "5402", "teacherName": "苏仕华", "periods": 2.0, "startIndex": 1, "endIndex": 2, "startHHMM": 750, "endHHMM": 925, "additionalInfo": {}}, {"startDate": 1308466200, "endDate": 1308472800, "name": "数据结构与数据库", "location": "5402", "teacherName": "苏仕华", "periods": 2.0, "startIndex": 7, "endIndex": 8, "startHHMM": 1450, "endHHMM": 1640, "additionalInfo": {}}, {"startDate": 1308786600, "endDate": 1308792300, "name": "数据结构与数据库", "location": "5402", "teacherName": "苏仕华", "periods": 2.0, "startIndex": 1, "endIndex": 2, "startHHMM": 750, "endHHMM": 925, "additionalInfo": {}}, {"startDate": 1309071000, "endDate": 1309077600, "name": "数据结构与数据库", "location": "5402", "teacherName": "苏仕华", "periods": 2.0, "startIndex": 7, "endIndex": 8, "startHHMM": 1450, "endHHMM": 1640, "additionalInfo": {}}, {"startDate": 1309391400, "endDate": 1309397100, "name": "数据结构与数据库", "location": "5402", "teacherName": "苏仕华", "periods": 2.0, "startIndex": 1, "endIndex": 2, "startHHMM": 750, "endHHMM": 925, "additionalInfo": {}}, {"startDate": 1309675800, "endDate": 1309682400, "name": "数据结构与数据库", "location": "5402", "teacherName": "苏仕华", "periods": 2.0, "startIndex": 7, "endIndex": 8, "startHHMM": 1450, "endHHMM": 1640, "additionalInfo": {}}], "exams": [], "dateTimePlacePersonText": "1~18周 5402 :4(1,2) 苏仕华\n2~19周 5402 :7(7,8) 苏仕华", "courseType": "理论实验课", "courseGradation": "通修", "courseCategory": "本科计划内课程", "educationType": "本科", "classType": "计划内与自由选修", "openDepartment": "信息科学技术学院", "description": "", "credit": 3.5, "additionalInfo": {}}