{"id": 100254, "name": "数字信号处理", "courseCode": "006187", "lessonCode": "006187.01", "teacherName": "卫国, 尹华锐", "lectures": [{"startDate": 1378447200, "endDate": 1378452900, "name": "数字信号处理", "location": "3A113", "teacherName": "尹华锐,卫国", "periods": 2.0, "startIndex": 6, "endIndex": 7, "startHHMM": 1400, "endHHMM": 1535, "additionalInfo": {}}, {"startDate": 1378454100, "endDate": 1378456800, "name": "数字信号处理", "location": "3A113", "teacherName": "尹华锐,卫国", "periods": 1.0, "startIndex": 8, "endIndex": 8, "startHHMM": 1555, "endHHMM": 1640, "additionalInfo": {}}, {"startDate": 1379052000, "endDate": 1379057700, "name": "数字信号处理", "location": "3A113", "teacherName": "尹华锐,卫国", "periods": 2.0, "startIndex": 6, "endIndex": 7, "startHHMM": 1400, "endHHMM": 1535, "additionalInfo": {}}, {"startDate": 1379058900, "endDate": 1379061600, "name": "数字信号处理", "location": "3A113", "teacherName": "尹华锐,卫国", "periods": 1.0, "startIndex": 8, "endIndex": 8, "startHHMM": 1555, "endHHMM": 1640, "additionalInfo": {}}, {"startDate": 1379656800, "endDate": 1379662500, "name": "数字信号处理", "location": "3A113", "teacherName": "尹华锐,卫国", "periods": 2.0, "startIndex": 6, "endIndex": 7, "startHHMM": 1400, "endHHMM": 1535, "additionalInfo": {}}, {"startDate": 1379663700, "endDate": 1379666400, "name": "数字信号处理", "location": "3A113", "teacherName": "尹华锐,卫国", "periods": 1.0, "startIndex": 8, "endIndex": 8, "startHHMM": 1555, "endHHMM": 1640, "additionalInfo": {}}, {"startDate": 1380261600, "endDate": 1380267300, "name": "数字信号处理", "location": "3A113", "teacherName": "尹华锐,卫国", "periods": 2.0, "startIndex": 6, "endIndex": 7, "startHHMM": 1400, "endHHMM": 1535, "additionalInfo": {}}, {"startDate": 1380268500, "endDate": 1380271200, "name": "数字信号处理", "location": "3A113", "teacherName": "尹华锐,卫国", "periods": 1.0, "startIndex": 8, "endIndex": 8, "startHHMM": 1555, "endHHMM": 1640, "additionalInfo": {}}, {"startDate": 1380866400, "endDate": 1380872100, "name": "数字信号处理", "location": "3A113", "teacherName": "尹华锐,卫国", "periods": 2.0, "startIndex": 6, "endIndex": 7, "startHHMM": 1400, "endHHMM": 1535, "additionalInfo": {}}, {"startDate": 1380873300, "endDate": 1380876000, "name": "数字信号处理", "location": "3A113", "teacherName": "尹华锐,卫国", "periods": 1.0, "startIndex": 8, "endIndex": 8, "startHHMM": 1555, "endHHMM": 1640, "additionalInfo": {}}, {"startDate": 1381471200, "endDate": 1381476900, "name": "数字信号处理", "location": "3A113", "teacherName": "尹华锐,卫国", "periods": 2.0, "startIndex": 6, "endIndex": 7, "startHHMM": 1400, "endHHMM": 1535, "additionalInfo": {}}, {"startDate": 1381478100, "endDate": 1381480800, "name": "数字信号处理", "location": "3A113", "teacherName": "尹华锐,卫国", "periods": 1.0, "startIndex": 8, "endIndex": 8, "startHHMM": 1555, "endHHMM": 1640, "additionalInfo": {}}, {"startDate": 1382076000, "endDate": 1382081700, "name": "数字信号处理", "location": "3A113", "teacherName": "尹华锐,卫国", "periods": 2.0, "startIndex": 6, "endIndex": 7, "startHHMM": 1400, "endHHMM": 1535, "additionalInfo": {}}, {"startDate": 1382082900, "endDate": 1382085600, "name": "数字信号处理", "location": "3A113", "teacherName": "尹华锐,卫国", "periods": 1.0, "startIndex": 8, "endIndex": 8, "startHHMM": 1555, "endHHMM": 1640, "additionalInfo": {}}, {"startDate": 1382680800, "endDate": 1382686500, "name": "数字信号处理", "location": "3A113", "teacherName": "尹华锐,卫国", "periods": 2.0, "startIndex": 6, "endIndex": 7, "startHHMM": 1400, "endHHMM": 1535, "additionalInfo": {}}, {"startDate": 1382687700, "endDate": 1382690400, "name": "数字信号处理", "location": "3A113", "teacherName": "尹华锐,卫国", "periods": 1.0, "startIndex": 8, "endIndex": 8, "startHHMM": 1555, "endHHMM": 1640, "additionalInfo": {}}, {"startDate": 1383285600, "endDate": 1383291300, "name": "数字信号处理", "location": "3A113", "teacherName": "尹华锐,卫国", "periods": 2.0, "startIndex": 6, "endIndex": 7, "startHHMM": 1400, "endHHMM": 1535, "additionalInfo": {}}, {"startDate": 1383292500, "endDate": 1383295200, "name": "数字信号处理", "location": "3A113", "teacherName": "尹华锐,卫国", "periods": 1.0, "startIndex": 8, "endIndex": 8, "startHHMM": 1555, "endHHMM": 1640, "additionalInfo": {}}, {"startDate": 1383890400, "endDate": 1383896100, "name": "数字信号处理", "location": "3A113", "teacherName": "尹华锐,卫国", "periods": 2.0, "startIndex": 6, "endIndex": 7, "startHHMM": 1400, "endHHMM": 1535, "additionalInfo": {}}, {"startDate": 1383897300, "endDate": 1383900000, "name": "数字信号处理", "location": "3A113", "teacherName": "尹华锐,卫国", "periods": 1.0, "startIndex": 8, "endIndex": 8, "startHHMM": 1555, "endHHMM": 1640, "additionalInfo": {}}, {"startDate": 1384495200, "endDate": 1384500900, "name": "数字信号处理", "location": "3A113", "teacherName": "尹华锐,卫国", "periods": 2.0, "startIndex": 6, "endIndex": 7, "startHHMM": 1400, "endHHMM": 1535, "additionalInfo": {}}, {"startDate": 1384502100, "endDate": 1384504800, "name": "数字信号处理", "location": "3A113", "teacherName": "尹华锐,卫国", "periods": 1.0, "startIndex": 8, "endIndex": 8, "startHHMM": 1555, "endHHMM": 1640, "additionalInfo": {}}, {"startDate": 1385100000, "endDate": 1385105700, "name": "数字信号处理", "location": "3A113", "teacherName": "尹华锐,卫国", "periods": 2.0, "startIndex": 6, "endIndex": 7, "startHHMM": 1400, "endHHMM": 1535, "additionalInfo": {}}, {"startDate": 1385106900, "endDate": 1385109600, "name": "数字信号处理", "location": "3A113", "teacherName": "尹华锐,卫国", "periods": 1.0, "startIndex": 8, "endIndex": 8, "startHHMM": 1555, "endHHMM": 1640, "additionalInfo": {}}, {"startDate": 1385704800, "endDate": 1385710500, "name": "数字信号处理", "location": "3A113", "teacherName": "尹华锐,卫国", "periods": 2.0, "startIndex": 6, "endIndex": 7, "startHHMM": 1400, "endHHMM": 1535, "additionalInfo": {}}, {"startDate": 1385711700, "endDate": 1385714400, "name": "数字信号处理", "location": "3A113", "teacherName": "尹华锐,卫国", "periods": 1.0, "startIndex": 8, "endIndex": 8, "startHHMM": 1555, "endHHMM": 1640, "additionalInfo": {}}, {"startDate": 1386309600, "endDate": 1386315300, "name": "数字信号处理", "location": "3A113", "teacherName": "尹华锐,卫国", "periods": 2.0, "startIndex": 6, "endIndex": 7, "startHHMM": 1400, "endHHMM": 1535, "additionalInfo": {}}, {"startDate": 1386316500, "endDate": 1386319200, "name": "数字信号处理", "location": "3A113", "teacherName": "尹华锐,卫国", "periods": 1.0, "startIndex": 8, "endIndex": 8, "startHHMM": 1555, "endHHMM": 1640, "additionalInfo": {}}, {"startDate": 1386914400, "endDate": 1386920100, "name": "数字信号处理", "location": "3A113", "teacherName": "尹华锐,卫国", "periods": 2.0, "startIndex": 6, "endIndex": 7, "startHHMM": 1400, "endHHMM": 1535, "additionalInfo": {}}, {"startDate": 1386921300, "endDate": 1386924000, "name": "数字信号处理", "location": "3A113", "teacherName": "尹华锐,卫国", "periods": 1.0, "startIndex": 8, "endIndex": 8, "startHHMM": 1555, "endHHMM": 1640, "additionalInfo": {}}, {"startDate": 1387519200, "endDate": 1387524900, "name": "数字信号处理", "location": "3A113", "teacherName": "尹华锐,卫国", "periods": 2.0, "startIndex": 6, "endIndex": 7, "startHHMM": 1400, "endHHMM": 1535, "additionalInfo": {}}, {"startDate": 1387526100, "endDate": 1387528800, "name": "数字信号处理", "location": "3A113", "teacherName": "尹华锐,卫国", "periods": 1.0, "startIndex": 8, "endIndex": 8, "startHHMM": 1555, "endHHMM": 1640, "additionalInfo": {}}, {"startDate": 1388124000, "endDate": 1388129700, "name": "数字信号处理", "location": "3A113", "teacherName": "尹华锐,卫国", "periods": 2.0, "startIndex": 6, "endIndex": 7, "startHHMM": 1400, "endHHMM": 1535, "additionalInfo": {}}, {"startDate": 1388130900, "endDate": 1388133600, "name": "数字信号处理", "location": "3A113", "teacherName": "尹华锐,卫国", "periods": 1.0, "startIndex": 8, "endIndex": 8, "startHHMM": 1555, "endHHMM": 1640, "additionalInfo": {}}, {"startDate": 1388728800, "endDate": 1388734500, "name": "数字信号处理", "location": "3A113", "teacherName": "尹华锐,卫国", "periods": 2.0, "startIndex": 6, "endIndex": 7, "startHHMM": 1400, "endHHMM": 1535, "additionalInfo": {}}, {"startDate": 1388735700, "endDate": 1388738400, "name": "数字信号处理", "location": "3A113", "teacherName": "尹华锐,卫国", "periods": 1.0, "startIndex": 8, "endIndex": 8, "startHHMM": 1555, "endHHMM": 1640, "additionalInfo": {}}, {"startDate": 1389333600, "endDate": 1389339300, "name": "数字信号处理", "location": "3A113", "teacherName": "尹华锐,卫国", "periods": 2.0, "startIndex": 6, "endIndex": 7, "startHHMM": 1400, "endHHMM": 1535, "additionalInfo": {}}, {"startDate": 1389340500, "endDate": 1389343200, "name": "数字信号处理", "location": "3A113", "teacherName": "尹华锐,卫国", "periods": 1.0, "startIndex": 8, "endIndex": 8, "startHHMM": 1555, "endHHMM": 1640, "additionalInfo": {}}, {"startDate": 1389938400, "endDate": 1389944100, "name": "数字信号处理", "location": "3A113", "teacherName": "尹华锐,卫国", "periods": 2.0, "startIndex": 6, "endIndex": 7, "startHHMM": 1400, "endHHMM": 1535, "additionalInfo": {}}, {"startDate": 1389945300, "endDate": 1389948000, "name": "数字信号处理", "location": "3A113", "teacherName": "尹华锐,卫国", "periods": 1.0, "startIndex": 8, "endIndex": 8, "startHHMM": 1555, "endHHMM": 1640, "additionalInfo": {}}], "exams": [], "dateTimePlacePersonText": "1~20周 3A113 :5(6,7) 尹华锐\n1~20周 3A113 :5(6,7) 卫国\n1~20周 3A113 :5(8) 尹华锐\n1~20周 3A113 :5(8) 卫国", "courseType": "理论课", "courseGradation": "专业核心", "courseCategory": "本科计划内课程", "educationType": "本科", "classType": "计划内与自由选修", "openDepartment": "电子工程与信息科学系", "description": "", "credit": 4.0, "additionalInfo": {}}