{"id": 148001, "name": "材料学科文献资源获取与检索", "courseCode": "MSEN6511P", "lessonCode": "MSEN6511P.01", "teacherName": "", "lectures": [{"startDate": 1680501600, "endDate": 1680507300, "name": "材料学科文献资源获取与检索", "location": "郭可信109", "teacherName": "", "periods": 2.0, "startIndex": 6, "endIndex": 7, "startHHMM": 1400, "endHHMM": 1535, "additionalInfo": {}}, {"startDate": 1680674400, "endDate": 1680680100, "name": "材料学科文献资源获取与检索", "location": "郭可信109", "teacherName": "", "periods": 2.0, "startIndex": 6, "endIndex": 7, "startHHMM": 1400, "endHHMM": 1535, "additionalInfo": {}}, {"startDate": 1680847200, "endDate": 1680852900, "name": "材料学科文献资源获取与检索", "location": "郭可信109", "teacherName": "", "periods": 2.0, "startIndex": 6, "endIndex": 7, "startHHMM": 1400, "endHHMM": 1535, "additionalInfo": {}}, {"startDate": 1681106400, "endDate": 1681112100, "name": "材料学科文献资源获取与检索", "location": "郭可信109", "teacherName": "", "periods": 2.0, "startIndex": 6, "endIndex": 7, "startHHMM": 1400, "endHHMM": 1535, "additionalInfo": {}}, {"startDate": 1681279200, "endDate": 1681284900, "name": "材料学科文献资源获取与检索", "location": "郭可信109", "teacherName": "", "periods": 2.0, "startIndex": 6, "endIndex": 7, "startHHMM": 1400, "endHHMM": 1535, "additionalInfo": {}}, {"startDate": 1681452000, "endDate": 1681457700, "name": "材料学科文献资源获取与检索", "location": "郭可信109", "teacherName": "", "periods": 2.0, "startIndex": 6, "endIndex": 7, "startHHMM": 1400, "endHHMM": 1535, "additionalInfo": {}}, {"startDate": 1681711200, "endDate": 1681716900, "name": "材料学科文献资源获取与检索", "location": "郭可信109", "teacherName": "", "periods": 2.0, "startIndex": 6, "endIndex": 7, "startHHMM": 1400, "endHHMM": 1535, "additionalInfo": {}}, {"startDate": 1681884000, "endDate": 1681889700, "name": "材料学科文献资源获取与检索", "location": "郭可信109", "teacherName": "", "periods": 2.0, "startIndex": 6, "endIndex": 7, "startHHMM": 1400, "endHHMM": 1535, "additionalInfo": {}}, {"startDate": 1682056800, "endDate": 1682062500, "name": "材料学科文献资源获取与检索", "location": "郭可信109", "teacherName": "", "periods": 2.0, "startIndex": 6, "endIndex": 7, "startHHMM": 1400, "endHHMM": 1535, "additionalInfo": {}}, {"startDate": 1682316000, "endDate": 1682321700, "name": "材料学科文献资源获取与检索", "location": "郭可信109", "teacherName": "", "periods": 2.0, "startIndex": 6, "endIndex": 7, "startHHMM": 1400, "endHHMM": 1535, "additionalInfo": {}}, {"startDate": 1682488800, "endDate": 1682494500, "name": "材料学科文献资源获取与检索", "location": "郭可信109", "teacherName": "", "periods": 2.0, "startIndex": 6, "endIndex": 7, "startHHMM": 1400, "endHHMM": 1535, "additionalInfo": {}}, {"startDate": 1682661600, "endDate": 1682667300, "name": "材料学科文献资源获取与检索", "location": "郭可信109", "teacherName": "", "periods": 2.0, "startIndex": 6, "endIndex": 7, "startHHMM": 1400, "endHHMM": 1535, "additionalInfo": {}}], "exams": [], "dateTimePlacePersonText": "5~8周 郭可信109 :1(6,7)\n5~8周 郭可信109 :3(6,7)\n5~8周 郭可信109 :5(6,7)", "courseType": "理论课", "courseGradation": "硕士", "courseCategory": "研究生课程", "educationType": "研究生", "classType": "基础", "openDepartment": "金属所", "description": "", "credit": 1.0, "additionalInfo": {}}