{"id": 97963, "name": "空气调节系统", "courseCode": "013147", "lessonCode": "013147.01", "teacherName": "季杰", "lectures": [{"startDate": 1267512600, "endDate": 1267519200, "name": "空气调节系统", "location": "", "teacherName": "季杰", "periods": 2.0, "startIndex": 7, "endIndex": 8, "startHHMM": 1450, "endHHMM": 1640, "additionalInfo": {}}, {"startDate": 1267746600, "endDate": 1267752300, "name": "空气调节系统", "location": "", "teacherName": "季杰", "periods": 2.0, "startIndex": 1, "endIndex": 2, "startHHMM": 750, "endHHMM": 925, "additionalInfo": {}}, {"startDate": 1268117400, "endDate": 1268124000, "name": "空气调节系统", "location": "", "teacherName": "季杰", "periods": 2.0, "startIndex": 7, "endIndex": 8, "startHHMM": 1450, "endHHMM": 1640, "additionalInfo": {}}, {"startDate": 1268351400, "endDate": 1268357100, "name": "空气调节系统", "location": "", "teacherName": "季杰", "periods": 2.0, "startIndex": 1, "endIndex": 2, "startHHMM": 750, "endHHMM": 925, "additionalInfo": {}}, {"startDate": 1268722200, "endDate": 1268728800, "name": "空气调节系统", "location": "", "teacherName": "季杰", "periods": 2.0, "startIndex": 7, "endIndex": 8, "startHHMM": 1450, "endHHMM": 1640, "additionalInfo": {}}, {"startDate": 1268956200, "endDate": 1268961900, "name": "空气调节系统", "location": "", "teacherName": "季杰", "periods": 2.0, "startIndex": 1, "endIndex": 2, "startHHMM": 750, "endHHMM": 925, "additionalInfo": {}}, {"startDate": 1269327000, "endDate": 1269333600, "name": "空气调节系统", "location": "", "teacherName": "季杰", "periods": 2.0, "startIndex": 7, "endIndex": 8, "startHHMM": 1450, "endHHMM": 1640, "additionalInfo": {}}, {"startDate": 1269561000, "endDate": 1269566700, "name": "空气调节系统", "location": "", "teacherName": "季杰", "periods": 2.0, "startIndex": 1, "endIndex": 2, "startHHMM": 750, "endHHMM": 925, "additionalInfo": {}}, {"startDate": 1269931800, "endDate": 1269938400, "name": "空气调节系统", "location": "", "teacherName": "季杰", "periods": 2.0, "startIndex": 7, "endIndex": 8, "startHHMM": 1450, "endHHMM": 1640, "additionalInfo": {}}, {"startDate": 1270165800, "endDate": 1270171500, "name": "空气调节系统", "location": "", "teacherName": "季杰", "periods": 2.0, "startIndex": 1, "endIndex": 2, "startHHMM": 750, "endHHMM": 925, "additionalInfo": {}}, {"startDate": 1270536600, "endDate": 1270543200, "name": "空气调节系统", "location": "", "teacherName": "季杰", "periods": 2.0, "startIndex": 7, "endIndex": 8, "startHHMM": 1450, "endHHMM": 1640, "additionalInfo": {}}, {"startDate": 1270770600, "endDate": 1270776300, "name": "空气调节系统", "location": "", "teacherName": "季杰", "periods": 2.0, "startIndex": 1, "endIndex": 2, "startHHMM": 750, "endHHMM": 925, "additionalInfo": {}}, {"startDate": 1271141400, "endDate": 1271148000, "name": "空气调节系统", "location": "", "teacherName": "季杰", "periods": 2.0, "startIndex": 7, "endIndex": 8, "startHHMM": 1450, "endHHMM": 1640, "additionalInfo": {}}, {"startDate": 1271375400, "endDate": 1271381100, "name": "空气调节系统", "location": "", "teacherName": "季杰", "periods": 2.0, "startIndex": 1, "endIndex": 2, "startHHMM": 750, "endHHMM": 925, "additionalInfo": {}}, {"startDate": 1271746200, "endDate": 1271752800, "name": "空气调节系统", "location": "", "teacherName": "季杰", "periods": 2.0, "startIndex": 7, "endIndex": 8, "startHHMM": 1450, "endHHMM": 1640, "additionalInfo": {}}, {"startDate": 1271980200, "endDate": 1271985900, "name": "空气调节系统", "location": "", "teacherName": "季杰", "periods": 2.0, "startIndex": 1, "endIndex": 2, "startHHMM": 750, "endHHMM": 925, "additionalInfo": {}}, {"startDate": 1272351000, "endDate": 1272357600, "name": "空气调节系统", "location": "", "teacherName": "季杰", "periods": 2.0, "startIndex": 7, "endIndex": 8, "startHHMM": 1450, "endHHMM": 1640, "additionalInfo": {}}, {"startDate": 1272585000, "endDate": 1272590700, "name": "空气调节系统", "location": "", "teacherName": "季杰", "periods": 2.0, "startIndex": 1, "endIndex": 2, "startHHMM": 750, "endHHMM": 925, "additionalInfo": {}}, {"startDate": 1272955800, "endDate": 1272962400, "name": "空气调节系统", "location": "", "teacherName": "季杰", "periods": 2.0, "startIndex": 7, "endIndex": 8, "startHHMM": 1450, "endHHMM": 1640, "additionalInfo": {}}, {"startDate": 1273189800, "endDate": 1273195500, "name": "空气调节系统", "location": "", "teacherName": "季杰", "periods": 2.0, "startIndex": 1, "endIndex": 2, "startHHMM": 750, "endHHMM": 925, "additionalInfo": {}}, {"startDate": 1273560600, "endDate": 1273567200, "name": "空气调节系统", "location": "", "teacherName": "季杰", "periods": 2.0, "startIndex": 7, "endIndex": 8, "startHHMM": 1450, "endHHMM": 1640, "additionalInfo": {}}, {"startDate": 1273794600, "endDate": 1273800300, "name": "空气调节系统", "location": "", "teacherName": "季杰", "periods": 2.0, "startIndex": 1, "endIndex": 2, "startHHMM": 750, "endHHMM": 925, "additionalInfo": {}}, {"startDate": 1274165400, "endDate": 1274172000, "name": "空气调节系统", "location": "", "teacherName": "季杰", "periods": 2.0, "startIndex": 7, "endIndex": 8, "startHHMM": 1450, "endHHMM": 1640, "additionalInfo": {}}, {"startDate": 1274399400, "endDate": 1274405100, "name": "空气调节系统", "location": "", "teacherName": "季杰", "periods": 2.0, "startIndex": 1, "endIndex": 2, "startHHMM": 750, "endHHMM": 925, "additionalInfo": {}}, {"startDate": 1274770200, "endDate": 1274776800, "name": "空气调节系统", "location": "", "teacherName": "季杰", "periods": 2.0, "startIndex": 7, "endIndex": 8, "startHHMM": 1450, "endHHMM": 1640, "additionalInfo": {}}, {"startDate": 1275004200, "endDate": 1275009900, "name": "空气调节系统", "location": "", "teacherName": "季杰", "periods": 2.0, "startIndex": 1, "endIndex": 2, "startHHMM": 750, "endHHMM": 925, "additionalInfo": {}}, {"startDate": 1275375000, "endDate": 1275381600, "name": "空气调节系统", "location": "", "teacherName": "季杰", "periods": 2.0, "startIndex": 7, "endIndex": 8, "startHHMM": 1450, "endHHMM": 1640, "additionalInfo": {}}, {"startDate": 1275609000, "endDate": 1275614700, "name": "空气调节系统", "location": "", "teacherName": "季杰", "periods": 2.0, "startIndex": 1, "endIndex": 2, "startHHMM": 750, "endHHMM": 925, "additionalInfo": {}}, {"startDate": 1275979800, "endDate": 1275986400, "name": "空气调节系统", "location": "", "teacherName": "季杰", "periods": 2.0, "startIndex": 7, "endIndex": 8, "startHHMM": 1450, "endHHMM": 1640, "additionalInfo": {}}, {"startDate": 1276213800, "endDate": 1276219500, "name": "空气调节系统", "location": "", "teacherName": "季杰", "periods": 2.0, "startIndex": 1, "endIndex": 2, "startHHMM": 750, "endHHMM": 925, "additionalInfo": {}}, {"startDate": 1276584600, "endDate": 1276591200, "name": "空气调节系统", "location": "", "teacherName": "季杰", "periods": 2.0, "startIndex": 7, "endIndex": 8, "startHHMM": 1450, "endHHMM": 1640, "additionalInfo": {}}, {"startDate": 1276818600, "endDate": 1276824300, "name": "空气调节系统", "location": "", "teacherName": "季杰", "periods": 2.0, "startIndex": 1, "endIndex": 2, "startHHMM": 750, "endHHMM": 925, "additionalInfo": {}}, {"startDate": 1277189400, "endDate": 1277196000, "name": "空气调节系统", "location": "", "teacherName": "季杰", "periods": 2.0, "startIndex": 7, "endIndex": 8, "startHHMM": 1450, "endHHMM": 1640, "additionalInfo": {}}, {"startDate": 1277423400, "endDate": 1277429100, "name": "空气调节系统", "location": "", "teacherName": "季杰", "periods": 2.0, "startIndex": 1, "endIndex": 2, "startHHMM": 750, "endHHMM": 925, "additionalInfo": {}}, {"startDate": 1277794200, "endDate": 1277800800, "name": "空气调节系统", "location": "", "teacherName": "季杰", "periods": 2.0, "startIndex": 7, "endIndex": 8, "startHHMM": 1450, "endHHMM": 1640, "additionalInfo": {}}, {"startDate": 1278028200, "endDate": 1278033900, "name": "空气调节系统", "location": "", "teacherName": "季杰", "periods": 2.0, "startIndex": 1, "endIndex": 2, "startHHMM": 750, "endHHMM": 925, "additionalInfo": {}}], "exams": [], "dateTimePlacePersonText": "1~18周 null :2(7,8) 季杰\n1~18周 null :5(1,2) 季杰", "courseType": "理论课", "courseGradation": "专业选修", "courseCategory": "本科计划内课程", "educationType": "本科", "classType": "计划内与自由选修", "openDepartment": "热科学和能源工程系", "description": "", "credit": 4.0, "additionalInfo": {}}