{"id": 157923, "name": "概率论与数理统计", "courseCode": "STAT2002", "lessonCode": "STAT2002.07", "teacherName": "刘杰", "lectures": [{"startDate": 1725327900, "endDate": 1725336600, "name": "概率论与数理统计", "location": "5401", "teacherName": "刘杰", "periods": 3.0, "startIndex": 3, "endIndex": 5, "startHHMM": 945, "endHHMM": 1210, "additionalInfo": {}}, {"startDate": 1725932700, "endDate": 1725941400, "name": "概率论与数理统计", "location": "5401", "teacherName": "刘杰", "periods": 3.0, "startIndex": 3, "endIndex": 5, "startHHMM": 945, "endHHMM": 1210, "additionalInfo": {}}, {"startDate": 1727142300, "endDate": 1727151000, "name": "概率论与数理统计", "location": "5401", "teacherName": "刘杰", "periods": 3.0, "startIndex": 3, "endIndex": 5, "startHHMM": 945, "endHHMM": 1210, "additionalInfo": {}}, {"startDate": 1727574300, "endDate": 1727583000, "name": "概率论与数理统计", "location": "5401", "teacherName": "刘杰", "periods": 3.0, "startIndex": 3, "endIndex": 5, "startHHMM": 945, "endHHMM": 1210, "additionalInfo": {}}, {"startDate": 1728351900, "endDate": 1728360600, "name": "概率论与数理统计", "location": "5401", "teacherName": "刘杰", "periods": 3.0, "startIndex": 3, "endIndex": 5, "startHHMM": 945, "endHHMM": 1210, "additionalInfo": {}}, {"startDate": 1728956700, "endDate": 1728965400, "name": "概率论与数理统计", "location": "5401", "teacherName": "刘杰", "periods": 3.0, "startIndex": 3, "endIndex": 5, "startHHMM": 945, "endHHMM": 1210, "additionalInfo": {}}, {"startDate": 1729561500, "endDate": 1729570200, "name": "概率论与数理统计", "location": "5401", "teacherName": "刘杰", "periods": 3.0, "startIndex": 3, "endIndex": 5, "startHHMM": 945, "endHHMM": 1210, "additionalInfo": {}}, {"startDate": 1730166300, "endDate": 1730175000, "name": "概率论与数理统计", "location": "5401", "teacherName": "刘杰", "periods": 3.0, "startIndex": 3, "endIndex": 5, "startHHMM": 945, "endHHMM": 1210, "additionalInfo": {}}, {"startDate": 1730771100, "endDate": 1730779800, "name": "概率论与数理统计", "location": "5401", "teacherName": "刘杰", "periods": 3.0, "startIndex": 3, "endIndex": 5, "startHHMM": 945, "endHHMM": 1210, "additionalInfo": {}}, {"startDate": 1731375900, "endDate": 1731384600, "name": "概率论与数理统计", "location": "5401", "teacherName": "刘杰", "periods": 3.0, "startIndex": 3, "endIndex": 5, "startHHMM": 945, "endHHMM": 1210, "additionalInfo": {}}, {"startDate": 1731980700, "endDate": 1731989400, "name": "概率论与数理统计", "location": "5401", "teacherName": "刘杰", "periods": 3.0, "startIndex": 3, "endIndex": 5, "startHHMM": 945, "endHHMM": 1210, "additionalInfo": {}}, {"startDate": 1732585500, "endDate": 1732594200, "name": "概率论与数理统计", "location": "5401", "teacherName": "刘杰", "periods": 3.0, "startIndex": 3, "endIndex": 5, "startHHMM": 945, "endHHMM": 1210, "additionalInfo": {}}, {"startDate": 1733190300, "endDate": 1733199000, "name": "概率论与数理统计", "location": "5401", "teacherName": "刘杰", "periods": 3.0, "startIndex": 3, "endIndex": 5, "startHHMM": 945, "endHHMM": 1210, "additionalInfo": {}}, {"startDate": 1733795100, "endDate": 1733803800, "name": "概率论与数理统计", "location": "5401", "teacherName": "刘杰", "periods": 3.0, "startIndex": 3, "endIndex": 5, "startHHMM": 945, "endHHMM": 1210, "additionalInfo": {}}, {"startDate": 1734399900, "endDate": 1734408600, "name": "概率论与数理统计", "location": "5401", "teacherName": "刘杰", "periods": 3.0, "startIndex": 3, "endIndex": 5, "startHHMM": 945, "endHHMM": 1210, "additionalInfo": {}}, {"startDate": 1735004700, "endDate": 1735013400, "name": "概率论与数理统计", "location": "5401", "teacherName": "刘杰", "periods": 3.0, "startIndex": 3, "endIndex": 5, "startHHMM": 945, "endHHMM": 1210, "additionalInfo": {}}, {"startDate": 1735609500, "endDate": 1735618200, "name": "概率论与数理统计", "location": "5401", "teacherName": "刘杰", "periods": 3.0, "startIndex": 3, "endIndex": 5, "startHHMM": 945, "endHHMM": 1210, "additionalInfo": {}}], "exams": [{"startDate": 1736490600, "endDate": 1736497800, "name": "概率论与数理统计", "location": "5402, 5401", "examType": "期末考试", "startHHMM": 1430, "endHHMM": 1630, "examMode": "笔试（闭卷）", "additionalInfo": {}}], "dateTimePlacePersonText": "1~2,4~6(双),7~18周 5401 :2(3,4,5) 刘杰\n5周 5401 :7(3,4,5) 刘杰", "courseType": "理论课", "courseGradation": "专业基础", "courseCategory": "本科计划内课程", "educationType": "本科", "classType": "计划内与自由选修", "openDepartment": "统计与金融系", "description": "", "credit": 3.0, "additionalInfo": {}}