{"id": 136016, "name": "管理研究哲学", "courseCode": "BUSI6104P", "lessonCode": "BUSI6104P.01", "teacherName": "刘志迎", "lectures": [{"startDate": 1631599200, "endDate": 1631611800, "name": "管理研究哲学", "location": "2404", "teacherName": "刘志迎", "periods": 4.0, "startIndex": 6, "endIndex": 9, "startHHMM": 1400, "endHHMM": 1730, "additionalInfo": {}}, {"startDate": 1632204000, "endDate": 1632216600, "name": "管理研究哲学", "location": "2404", "teacherName": "刘志迎", "periods": 4.0, "startIndex": 6, "endIndex": 9, "startHHMM": 1400, "endHHMM": 1730, "additionalInfo": {}}, {"startDate": 1632808800, "endDate": 1632821400, "name": "管理研究哲学", "location": "2404", "teacherName": "刘志迎", "periods": 4.0, "startIndex": 6, "endIndex": 9, "startHHMM": 1400, "endHHMM": 1730, "additionalInfo": {}}, {"startDate": 1633413600, "endDate": 1633426200, "name": "管理研究哲学", "location": "2404", "teacherName": "刘志迎", "periods": 4.0, "startIndex": 6, "endIndex": 9, "startHHMM": 1400, "endHHMM": 1730, "additionalInfo": {}}, {"startDate": 1634018400, "endDate": 1634031000, "name": "管理研究哲学", "location": "2404", "teacherName": "刘志迎", "periods": 4.0, "startIndex": 6, "endIndex": 9, "startHHMM": 1400, "endHHMM": 1730, "additionalInfo": {}}, {"startDate": 1634623200, "endDate": 1634635800, "name": "管理研究哲学", "location": "2404", "teacherName": "刘志迎", "periods": 4.0, "startIndex": 6, "endIndex": 9, "startHHMM": 1400, "endHHMM": 1730, "additionalInfo": {}}, {"startDate": 1635228000, "endDate": 1635240600, "name": "管理研究哲学", "location": "2404", "teacherName": "刘志迎", "periods": 4.0, "startIndex": 6, "endIndex": 9, "startHHMM": 1400, "endHHMM": 1730, "additionalInfo": {}}, {"startDate": 1635832800, "endDate": 1635845400, "name": "管理研究哲学", "location": "2404", "teacherName": "刘志迎", "periods": 4.0, "startIndex": 6, "endIndex": 9, "startHHMM": 1400, "endHHMM": 1730, "additionalInfo": {}}, {"startDate": 1636437600, "endDate": 1636450200, "name": "管理研究哲学", "location": "2404", "teacherName": "刘志迎", "periods": 4.0, "startIndex": 6, "endIndex": 9, "startHHMM": 1400, "endHHMM": 1730, "additionalInfo": {}}, {"startDate": 1637042400, "endDate": 1637055000, "name": "管理研究哲学", "location": "2404", "teacherName": "刘志迎", "periods": 4.0, "startIndex": 6, "endIndex": 9, "startHHMM": 1400, "endHHMM": 1730, "additionalInfo": {}}], "exams": [], "dateTimePlacePersonText": "2~11周 2404 :2(6,7,8,9) 刘志迎", "courseType": "理论课", "courseGradation": "硕士", "courseCategory": "研究生课程", "educationType": "研究生", "classType": "基础", "openDepartment": "管理学院", "description": "", "credit": 2.0, "additionalInfo": {}}