{"id": 116582, "name": "普通地质学", "courseCode": "007225", "lessonCode": "007225.01", "teacherName": "谢智", "lectures": [{"startDate": 1551420000, "endDate": 1551429600, "name": "普通地质学", "location": "2403", "teacherName": "谢智", "periods": 3.0, "startIndex": 6, "endIndex": 8, "startHHMM": 1400, "endHHMM": 1640, "additionalInfo": {}}, {"startDate": 1552024800, "endDate": 1552034400, "name": "普通地质学", "location": "2403", "teacherName": "谢智", "periods": 3.0, "startIndex": 6, "endIndex": 8, "startHHMM": 1400, "endHHMM": 1640, "additionalInfo": {}}, {"startDate": 1552629600, "endDate": 1552639200, "name": "普通地质学", "location": "2403", "teacherName": "谢智", "periods": 3.0, "startIndex": 6, "endIndex": 8, "startHHMM": 1400, "endHHMM": 1640, "additionalInfo": {}}, {"startDate": 1553234400, "endDate": 1553244000, "name": "普通地质学", "location": "2403", "teacherName": "谢智", "periods": 3.0, "startIndex": 6, "endIndex": 8, "startHHMM": 1400, "endHHMM": 1640, "additionalInfo": {}}, {"startDate": 1553839200, "endDate": 1553848800, "name": "普通地质学", "location": "2403", "teacherName": "谢智", "periods": 3.0, "startIndex": 6, "endIndex": 8, "startHHMM": 1400, "endHHMM": 1640, "additionalInfo": {}}, {"startDate": 1554444000, "endDate": 1554453600, "name": "普通地质学", "location": "2403", "teacherName": "谢智", "periods": 3.0, "startIndex": 6, "endIndex": 8, "startHHMM": 1400, "endHHMM": 1640, "additionalInfo": {}}, {"startDate": 1555048800, "endDate": 1555058400, "name": "普通地质学", "location": "2403", "teacherName": "谢智", "periods": 3.0, "startIndex": 6, "endIndex": 8, "startHHMM": 1400, "endHHMM": 1640, "additionalInfo": {}}, {"startDate": 1555653600, "endDate": 1555663200, "name": "普通地质学", "location": "2403", "teacherName": "谢智", "periods": 3.0, "startIndex": 6, "endIndex": 8, "startHHMM": 1400, "endHHMM": 1640, "additionalInfo": {}}, {"startDate": 1556258400, "endDate": 1556268000, "name": "普通地质学", "location": "2403", "teacherName": "谢智", "periods": 3.0, "startIndex": 6, "endIndex": 8, "startHHMM": 1400, "endHHMM": 1640, "additionalInfo": {}}, {"startDate": 1557036000, "endDate": 1557045600, "name": "普通地质学", "location": "2403", "teacherName": "谢智", "periods": 3.0, "startIndex": 6, "endIndex": 8, "startHHMM": 1400, "endHHMM": 1640, "additionalInfo": {}}, {"startDate": 1557468000, "endDate": 1557477600, "name": "普通地质学", "location": "2403", "teacherName": "谢智", "periods": 3.0, "startIndex": 6, "endIndex": 8, "startHHMM": 1400, "endHHMM": 1640, "additionalInfo": {}}, {"startDate": 1558072800, "endDate": 1558082400, "name": "普通地质学", "location": "2403", "teacherName": "谢智", "periods": 3.0, "startIndex": 6, "endIndex": 8, "startHHMM": 1400, "endHHMM": 1640, "additionalInfo": {}}, {"startDate": 1558677600, "endDate": 1558687200, "name": "普通地质学", "location": "2403", "teacherName": "谢智", "periods": 3.0, "startIndex": 6, "endIndex": 8, "startHHMM": 1400, "endHHMM": 1640, "additionalInfo": {}}, {"startDate": 1559282400, "endDate": 1559292000, "name": "普通地质学", "location": "2403", "teacherName": "谢智", "periods": 3.0, "startIndex": 6, "endIndex": 8, "startHHMM": 1400, "endHHMM": 1640, "additionalInfo": {}}], "exams": [{"startDate": 1561962600, "endDate": 1561971600, "name": "普通地质学", "location": "2210", "examType": "期末考试", "startHHMM": 1430, "endHHMM": 1700, "examMode": "闭卷", "additionalInfo": {}}], "dateTimePlacePersonText": "1~9,11~14周 2403 :5(6,7,8) 谢智\n11周 2403 :7(6,7,8) 谢智", "courseType": "理论课", "courseGradation": "专业基础", "courseCategory": "本科计划内课程", "educationType": "本科", "classType": "计划内与自由选修", "openDepartment": "地球和空间科学学院", "description": "", "credit": 2.0, "additionalInfo": {}}